{
  "project_info": {
    "project_number": "1003803911785",
    "project_id": "boothtify-app",
    "storage_bucket": "boothtify-app.firebasestorage.app"
  },
  "client": [
    {
      "client_info": {
        "mobilesdk_app_id": "1:1003803911785:android:a41453c1583347d191e4f8",
        "android_client_info": {
          "package_name": "com.example.myapp"
        }
      },
      "oauth_client": [],
      "api_key": [
        {
          "current_key": "AIzaSyDHqCOZjG5yOHt7FbsfKJ7DV-_5EjU-RK0"
        }
      ],
      "services": {
        "appinvite_service": {
          "other_platform_oauth_client": []
        }
      }
    }
  ],
  "configuration_version": "1"
}